{
	"format_version": "1.12.0",
	"minecraft:geometry": [
		{
			"description": {
				"identifier": "geometry.splaturn.splash_o_matic",
				"texture_width": 32,
				"texture_height": 32,
				"visible_bounds_width": 4,
				"visible_bounds_height": 2,
				"visible_bounds_offset": [0, 1, 0]
			},
			"bones": [
				{
					"name": "body",
					"pivot": [0, 24, 0]
				},
				{
					"name": "bodyArmor",
					"parent": "body",
					"pivot": [0, 24, 0]
				},
				{
					"name": "belt",
					"parent": "body",
					"pivot": [0, 24, 0]
				},
				{
					"name": "waist",
					"pivot": [0, 12, 0]
				},
				{
					"name": "head",
					"pivot": [0, 24, 0]
				},
				{
					"name": "hat",
					"pivot": [0, 24, 0]
				},
				{
					"name": "rightArm",
					"pivot": [-5, 22, 0]
				},
				{
					"name": "rightItem",
					"parent": "rightArm",
					"pivot": [-6, 15, 1]
				},
				{
					"name": "rightArmArmor",
					"parent": "rightArm",
					"pivot": [-5, 22, 0]
				},
				{
					"name": "weapon",
					"parent": "rightArm",
					"pivot": [-6, 14, -2],
					"rotation": [60, 0, 0]
				},
				{
					"name": "tank",
					"parent": "weapon",
					"pivot": [1, 0, 9],
					"cubes": [
						{"origin": [-6, 17, -10], "size": [1, 1, 12], "inflate": 0.2, "uv": [0, 0]}
					]
				},
				{
					"name": "holder",
					"parent": "weapon",
					"pivot": [-6, 17.75, -2],
					"cubes": [
						{"origin": [-6.5, 15, -7], "size": [2, 4, 1], "uv": [0, 0]},
						{"origin": [-6.5, 17, 0], "size": [2, 2, 1], "uv": [0, 0]},
						{"origin": [-6, 18, -9], "size": [1, 2, 1], "uv": [0, 0]},
						{"origin": [-6, 15, -9], "size": [1, 2, 1], "uv": [0, 0]},
						{"origin": [-6, 17.75, -6], "size": [1, 2, 2], "uv": [17, 13]},
						{"origin": [-6, 18.75, -4], "size": [1, 1, 1], "uv": [0, 0]}
					]
				},
				{
					"name": "bone",
					"parent": "holder",
					"pivot": [-5.5, 19.25, -1.5],
					"rotation": [-10, 0, 0],
					"cubes": [
						{"origin": [-6, 18.75, -4], "size": [1, 1, 5], "uv": [0, 0]}
					]
				},
				{
					"name": "handle",
					"parent": "weapon",
					"pivot": [1, 0, 9],
					"cubes": [
						{"origin": [-6, 14.92661, -6.76753], "size": [1, 1, 5], "uv": [0, 0]},
						{"origin": [-6, 13.4, -3.7], "size": [1, 2, 2], "uv": [0, 0]}
					]
				},
				{
					"name": "connector",
					"parent": "handle",
					"pivot": [-6, 16.22661, -0.76753],
					"rotation": [30, 0, 0],
					"cubes": [
						{"origin": [-6, 15.72661, -2.26753], "size": [1, 1, 3], "uv": [0, 0]}
					]
				},
				{
					"name": "laucher",
					"parent": "weapon",
					"pivot": [-6, 18, -9],
					"cubes": [
						{"origin": [-6, 17, -12], "size": [1, 1, 3], "inflate": -0.2, "uv": [0, 0]}
					]
				},
				{
					"name": "leftArm",
					"pivot": [5, 22, 0],
					"mirror": true
				},
				{
					"name": "leftArmArmor",
					"parent": "leftArm",
					"pivot": [5, 22, 0],
					"mirror": true
				},
				{
					"name": "rightLeg",
					"pivot": [-1.9, 12, 0]
				},
				{
					"name": "rightLegging",
					"parent": "rightLeg",
					"pivot": [-1.9, 12, 0]
				},
				{
					"name": "rightBoot",
					"parent": "rightLeg",
					"pivot": [-1.9, 12, 0]
				},
				{
					"name": "rightSock",
					"parent": "rightLeg",
					"pivot": [-1.9, 12, 0]
				},
				{
					"name": "leftLeg",
					"pivot": [1.9, 12, 0],
					"mirror": true
				},
				{
					"name": "leftLegging",
					"parent": "leftLeg",
					"pivot": [1.9, 12, 0],
					"mirror": true
				},
				{
					"name": "leftBoot",
					"parent": "leftLeg",
					"pivot": [1.9, 12, 0],
					"mirror": true
				},
				{
					"name": "leftSock",
					"parent": "leftLeg",
					"pivot": [1.9, 12, 0],
					"mirror": true
				},
				{
					"name": "helmet",
					"pivot": [0, 24, 0]
				}
			]
		}
	]
}